markdown_wavedrom/__init__.py
markdown_wavedrom/extension.py
markdown_wavedrom-1.0.0.dist-info/LICENSE
markdown_wavedrom-1.0.0.dist-info/METADATA
markdown_wavedrom-1.0.0.dist-info/WHEEL
markdown_wavedrom-1.0.0.dist-info/top_level.txt
markdown_wavedrom-1.0.0.dist-info/zip-safe
markdown_wavedrom-1.0.0.dist-info/RECORD
