Metadata-Version: 2.1
Name: markdown-wavedrom
Version: 1.0.0
Summary: Support for WaveDrom in Python Markdown
Home-page: https://github.com/MaximilianKoestler/markdown-wavedrom
Author: Maximilian Köstler
Author-email: maximilian@koestler.dev
License: MIT License
Keywords: Markdown,WaveDrom,MkDocs
Platform: UNKNOWN
Classifier: Development Status :: 5 - Production/Stable
Classifier: Environment :: Console
Classifier: Intended Audience :: Developers
Classifier: License :: OSI Approved :: MIT License
Classifier: Operating System :: OS Independent
Classifier: Programming Language :: Python
Classifier: Programming Language :: Python :: 3.6
Classifier: Programming Language :: Python :: 3.7
Classifier: Programming Language :: Python :: 3.8
Classifier: Programming Language :: Python :: 3.9
Classifier: Programming Language :: Python :: Implementation :: CPython
Classifier: Programming Language :: Python :: Implementation :: PyPy
Classifier: Topic :: Documentation
Classifier: Topic :: Software Development :: Libraries :: Python Modules
Classifier: Topic :: Text Processing :: Markup :: HTML
Classifier: Topic :: Text Processing :: Markup :: Markdown
Classifier: Topic :: Utilities
Requires-Python: >=3.6
Requires-Dist: Markdown
